prr/__init__.py
prr/__main__.py
prr/commands/run.py
prr/commands/ui.py
prr/commands/watch.py
prr/prompt/__init__.py
prr/prompt/model_options.py
prr/prompt/prompt_config.py
prr/prompt/prompt_loader.py
prr/prompt/prompt_template.py
prr/prompt/service_config.py
prr/prompt_template.yaml
prr/runner/__init__.py
prr/runner/prompt_run.py
prr/runner/prompt_run_result.py
prr/runner/run_collection.py
prr/runner/saved_prompt_run.py
prr/runner/saved_service_run.py
prr/services/providers/anthropic/complete.py
prr/services/providers/bigcode/starcoder.py
prr/services/providers/elevenlabs/tts.py
prr/services/providers/google/chat.py
prr/services/providers/google/complete.py
prr/services/providers/openai/chat.py
prr/services/providers/test/test_service.py
prr/services/service_base.py
prr/services/service_registry.py
prr/ui/__init__.py
prr/ui/prompt_files.py
prr/ui/routers/diff.py
prr/ui/routers/edit.py
prr/ui/routers/runs.py
prr/ui/routers/state.py
prr/ui/static/css/index.css
prr/ui/static/monaco-editor/CHANGELOG.md
prr/ui/static/monaco-editor/LICENSE
prr/ui/static/monaco-editor/README.md
prr/ui/static/monaco-editor/ThirdPartyNotices.txt
prr/ui/static/monaco-editor/min/vs/base/browser/ui/codicons/codicon/codicon.ttf
prr/ui/static/monaco-editor/min/vs/base/common/worker/simpleWorker.nls.de.js
prr/ui/static/monaco-editor/min/vs/base/common/worker/simpleWorker.nls.es.js
prr/ui/static/monaco-editor/min/vs/base/common/worker/simpleWorker.nls.fr.js
prr/ui/static/monaco-editor/min/vs/base/common/worker/simpleWorker.nls.it.js
prr/ui/static/monaco-editor/min/vs/base/common/worker/simpleWorker.nls.ja.js
prr/ui/static/monaco-editor/min/vs/base/common/worker/simpleWorker.nls.js
prr/ui/static/monaco-editor/min/vs/base/common/worker/simpleWorker.nls.ko.js
prr/ui/static/monaco-editor/min/vs/base/common/worker/simpleWorker.nls.ru.js
prr/ui/static/monaco-editor/min/vs/base/common/worker/simpleWorker.nls.zh-cn.js
prr/ui/static/monaco-editor/min/vs/base/common/worker/simpleWorker.nls.zh-tw.js
prr-0.4.0.dist-info/LICENSE
prr-0.4.0.dist-info/METADATA
prr-0.4.0.dist-info/WHEEL
prr-0.4.0.dist-info/entry_points.txt
prr-0.4.0.dist-info/RECORD
