Metadata-Version: 2.1
Name: prr
Version: 0.4.0
Summary: prr - command-line LLM prompt runner
License: MIT
Author: Zbigniew Sobiecki
Author-email: zbigniew@fwdoperators.com
Requires-Python: >=3.9,<4.0
Classifier: License :: OSI Approved :: MIT License
Classifier: Programming Language :: Python :: 3
Classifier: Programming Language :: Python :: 3.9
Classifier: Programming Language :: Python :: 3.10
Classifier: Programming Language :: Python :: 3.11
Requires-Dist: Jinja2 (>=3.1.2,<4.0.0)
Requires-Dist: anthropic (>=0.2.7,<0.3.0)
Requires-Dist: elevenlabs (>=0.2.21,<0.3.0)
Requires-Dist: fastapi (>=0.100.0,<0.101.0)
Requires-Dist: google-cloud-aiplatform (>=1.25.0,<2.0.0)
Requires-Dist: huggingface-hub (>=0.14.1,<0.15.0)
Requires-Dist: openai (>=0.27.6,<0.28.0)
Requires-Dist: python-dotenv (>=1.0.0,<2.0.0)
Requires-Dist: pyyaml (>=6.0,<7.0)
Requires-Dist: rich (>=13.3.5,<14.0.0)
Requires-Dist: text-generation (>=0.5.2,<0.6.0)
Requires-Dist: uvicorn (>=0.22.0,<0.23.0)
